CHANGELOG.md
LICENSE
MANIFEST.in
README.md
setup.py
django_tesseractfield.egg-info/PKG-INFO
django_tesseractfield.egg-info/SOURCES.txt
django_tesseractfield.egg-info/dependency_links.txt
django_tesseractfield.egg-info/requires.txt
django_tesseractfield.egg-info/top_level.txt
tesseractfield/__init__.py
tesseractfield/fields.py
tesseractfield/tesseract.py
tesseractfield/urls.py
tesseractfield/views.py
tesseractfield/static/tesseractfield/css/tesseract.css
tesseractfield/static/tesseractfield/js/tesseract.js
tesseractfield/templates/tesseractfield/tesseract.html