Metadata-Version: 2.1
Name: django-tesseractfield
Version: 0.0.2
Summary: A small app providing a tesseract field for django
Home-page: http://github.com/duboisR/django-tesseractfield
Author: Dubois Romain
Author-email: dubois.rom@gmail.com
License: MIT License
Keywords: django,tesseract,field,admin
Platform: UNKNOWN
Classifier: Development Status :: 4 - Beta
Classifier: License :: OSI Approved :: MIT License
Classifier: Framework :: Django :: 2.0
Classifier: Programming Language :: Python :: 3.5
Requires: django (>=2.0)
